MANIFEST.in
README.html
README.rst
hello_trace.py
ordereddict.py
otrace.py
setup.py
demo/Receive.respond.patch
demo/hello_test.osh
docs/FAQ.rst
docs/GettingStarted.html
docs/GettingStarted.rst
docs/UseWithTornado.rst
otrace.egg-info/PKG-INFO
otrace.egg-info/SOURCES.txt
otrace.egg-info/dependency_links.txt
otrace.egg-info/entry_points.txt
otrace.egg-info/top_level.txt
tornademos/chat_trace.py
tornademos/chat_websock.py
tornademos/otrace.py
tornademos/torna_trace.py
tornademos/static/chat.css
tornademos/static/chat.js
tornademos/static/chat_ws.js
tornademos/templates/index.html
tornademos/templates/index_ws.html
tornademos/templates/message.html