Metadata-Version: 1.0
Name: otrace
Version: 0.30.9
Summary: otrace: An object-oriented debugger for nonlinear tracing
Home-page: http://info.mindmeldr.com/code/otrace
Author: Ramalingam Saravanan
Author-email: sarava@sarava.net
License: BSD License
Download-URL: https://github.com/mitotic/otrace/tags
Keywords: debugging,shell,tracing
Platform: UNKNOWN
Classifier: Development Status :: 3 - Alpha
Classifier: Environment :: Console
Classifier: Intended Audience :: Developers
Classifier: License :: OSI Approved :: BSD License
Classifier: Operating System :: OS Independent
Classifier: Programming Language :: Python
Classifier: Programming Language :: Python :: 3
Classifier: Topic :: Software Development :: Debuggers
Classifier: Topic :: Software Development :: Libraries :: Python Modules
Classifier: Topic :: System :: Monitoring
Classifier: Topic :: System :: Shells
